wolf_libs/MSVCP140.dll
wolf_libs/WolfDll.dll
wolf_libs/Wolf_tools.dll
wolf_libs/__init__.py
wolf_libs/api-ms-win-crt-heap-l1-1-0.dll
wolf_libs/api-ms-win-crt-math-l1-1-0.dll
wolf_libs/api-ms-win-crt-runtime-l1-1-0.dll
wolf_libs/fribidi-0.dll
wolf_libs/get_infos.cp310-win_amd64.pyd
wolf_libs/get_infos.cp311-win_amd64.pyd
wolf_libs/get_infos.cp312-win_amd64.pyd
wolf_libs/get_infos.cp313-win_amd64.pyd
wolf_libs/glu32.dll
wolf_libs/hdf5.dll
wolf_libs/hdf5_hl.dll
wolf_libs/libcurl.dll
wolf_libs/libpardiso600-WIN-X86-64.dll
wolf_libs/libraqm.dll
wolf_libs/msvcr100.dll
wolf_libs/netcdf.dll
wolf_libs/paho-mqtt3cs.dll
wolf_libs/vcomp100.dll
wolf_libs/vcruntime140.dll
wolf_libs/vcruntime140_1.dll
wolf_libs/verify_wolf.cp310-win_amd64.pyd
wolf_libs/verify_wolf.cp311-win_amd64.pyd
wolf_libs/verify_wolf.cp312-win_amd64.pyd
wolf_libs/verify_wolf.cp313-win_amd64.pyd
wolf_libs/wolfogl.cp310-win_amd64.pyd
wolf_libs/wolfogl.cp311-win_amd64.pyd
wolf_libs/wolfogl.cp312-win_amd64.pyd
wolf_libs/wolfogl.cp313-win_amd64.pyd
wolf_libs/zlib1.dll
wolf_libs/GL/gl.h
wolf_libs/GL/glaux.h
wolf_libs/GL/glcorearb.h
wolf_libs/GL/glext.h
wolf_libs/GL/glu.h
wolf_libs/GL/glxext.h
wolf_libs/GL/wglext.h
wolf_libs-0.0.1.dist-info/METADATA
wolf_libs-0.0.1.dist-info/WHEEL
wolf_libs-0.0.1.dist-info/top_level.txt
wolf_libs-0.0.1.dist-info/RECORD
