Metadata-Version: 2.4
Name: wolf_libs
Version: 0.0.1
Author-email: Pierre Archambeau <pierre.archambeau@uliege.be>
Project-URL: Homepage, https://uee.uliege.be/hece
Project-URL: Issues, https://uee.uliege.be/hece
Classifier: Programming Language :: Python :: 3.10
Classifier: Programming Language :: Python :: 3.11
Classifier: Programming Language :: Python :: 3.12
Classifier: Operating System :: Microsoft :: Windows :: Windows 10
Classifier: Operating System :: Microsoft :: Windows :: Windows 11
Classifier: Operating System :: POSIX :: Linux
Classifier: Topic :: Scientific/Engineering :: Physics
Requires-Python: <3.13,>=3.10
Requires-Dist: msvc-runtime
Requires-Dist: intel-fortran-rt
Requires-Dist: cryptography
Requires-Dist: cython
Requires-Dist: beautifulsoup4
Requires-Dist: requests
Requires-Dist: mkl
